cli/__init__.py
pattern_cli-0.0.2.data/data/requirements.txt
pattern_cli-0.0.2.dist-info/LICENSE
pattern_cli-0.0.2.dist-info/METADATA
pattern_cli-0.0.2.dist-info/WHEEL
pattern_cli-0.0.2.dist-info/top_level.txt
pattern_cli-0.0.2.dist-info/RECORD
