Metadata-Version: 2.1
Name: pattern-cli
Version: 0.0.2
Summary: Make command-line interface scripts with ease
Home-page: https://github.com/HashLDash/cli
Author: HashLDash
Author-email: HashLDash <digameoquepensas@gmail.com>
Project-URL: Homepage, https://github.com/HashLDash/cli
Project-URL: Bug Tracker, https://github.com/HashLDash/cli/issues
Classifier: Programming Language :: Python :: 3
Classifier: License :: OSI Approved :: MIT License
Classifier: Operating System :: OS Independent
Requires-Python: >=3.6
License-File: LICENSE
